{
  "parent": "quest_giver:quest_0074_01",
  "reputation": 4,
  "icon": "minecraft:book",
  "start": {
    "title": {
      "text": "さて？"
    },
    "description": {
      "text": "あなたの$(red)精霊 orb$()がもう一つ必要です。"
    }
  },
  "complete": {
    "title": {
      "text": "ありがとう！"
    },
    "description": {
      "text": "はは…若者よ、お前はお人好しすぎる。あまり話したことのない相手に信頼を寄せるな。気の毒に思うからオーブは返すが、これだけは覚えておけ：みんなが私のように優しいわけではない。"
    }
  },
  "tasks": [
     {
      "item": {
	 "item": "paraglider:spirit_orb"
      },
      "id": "quest_giver:gift",
      "times": 1
     }
  ],
  "rewards": [
    {
      "command": "/addreputation reputation:villager @p 2",
      "id": "quest_giver:command"
    },
    {
      "item": {
        "item": "paraglider:spirit_orb"
      },
      "id": "quest_giver:item",
      "times": 2
    },
    {
      "item": {
        "item": "minecraft:cookie"
      },
      "id": "quest_giver:item",
      "times": 1
    }
  ]
}